.DS_Store
coursera_gdrive/CourseraDownloader.py
coursera_gdrive/__init__.py
coursera_gdrive/lib/language_codes.csv
coursera_GDrive-0.0.3.dist-info/LICENSE
coursera_GDrive-0.0.3.dist-info/METADATA
coursera_GDrive-0.0.3.dist-info/WHEEL
coursera_GDrive-0.0.3.dist-info/top_level.txt
coursera_GDrive-0.0.3.dist-info/RECORD
