Metadata-Version: 2.1
Name: coursera-GDrive
Version: 0.0.3
Summary: This small project is helpful for downloading Coursera courses into your Google Drive via Google Colab.
Home-page: https://github.com/kaanaritr/Coursera-GDrive
Author: Kaan ARI
Author-email: kaan.ari.tr@gmail.com
License: LGPLv3
Project-URL: Documentation, https://github.com/kaanaritr/Coursera-GDrive
Project-URL: Say Thanks!, https://github.com/coursera-dl/coursera-dl
Project-URL: Source, https://github.com/kaanaritr/Coursera-GDrive
Keywords: coursera-dl,coursera,download,education,MOOCs,google-drive
Platform: UNKNOWN
Classifier: Development Status :: 2 - Pre-Alpha
Classifier: Programming Language :: Python :: 3
Classifier: License :: OSI Approved :: GNU General Public License v3 (GPLv3)
Classifier: Operating System :: OS Independent
Classifier: Environment :: Other Environment
Requires-Python: >=3.0
Requires-Dist: coursera-dl (>=0.11.0)
